stfu/__init__.py
stfu/cli.py
stfu/parser.py
stfu/terraform.py
stfu_terraform-0.1.0.dist-info/licenses/LICENSE
stfu_terraform-0.1.0.dist-info/METADATA
stfu_terraform-0.1.0.dist-info/WHEEL
stfu_terraform-0.1.0.dist-info/entry_points.txt
stfu_terraform-0.1.0.dist-info/top_level.txt
stfu_terraform-0.1.0.dist-info/RECORD
